Metadata-Version: 2.1
Name: pclimareq2
Version: 0.0.1
Summary: Módulo para recuperação de dados climáticos do PCBr.
Home-page: https://github.com/felipeodorizi/pclima
Author: Felipe Odorizi de Mello
Author-email: felipeodorizi@gmail.com
License: MIT
Project-URL: Código fonte, https://github.com/felipeodorizi/pclima
Project-URL: Download, https://github.com/felipeodorizi/pclima/pclima-1.0.0.tar.gz
Keywords: recuperação de dados climáticos
Platform: UNKNOWN
Classifier: Development Status :: 5 - Production/Stable
Classifier: Intended Audience :: Developers
Classifier: License :: OSI Approved :: MIT License
Classifier: Natural Language :: Portuguese (Brazilian)
Classifier: Operating System :: OS Independent
Classifier: Topic :: Software Development :: Internationalization
Classifier: Topic :: Scientific/Engineering :: Physics
